setup.py
distributions_Jason/Binomialdistribution.py
distributions_Jason/Gaussiandistribution.py
distributions_Jason/Generaldistribution.py
distributions_Jason/__init__.py
distributions_Jason.egg-info/PKG-INFO
distributions_Jason.egg-info/SOURCES.txt
distributions_Jason.egg-info/dependency_links.txt
distributions_Jason.egg-info/not-zip-safe
distributions_Jason.egg-info/top_level.txt