Metadata-Version: 1.0
Name: distributions-Jason
Version: 0.1
Summary: Gaussian distributions
Home-page: UNKNOWN
Author: JasonShin
Author-email: kimgaul.js@gmail.com
License: UNKNOWN
Platform: UNKNOWN
